{
  "ret": true,
  "data": {
    "marketingActivityList": [],
    "isQunarStraightSale": true,
    "supplierNameInfo": {
      "supplierName": "去哪儿直销",
      "supplierId": "11488",
      "enterGardenTag": {
        "imgUrl": "https://img1.qunarzz.com/piao/fusion/1703/d2/a9f4fda324b31e02.png",
        "desc": "入园保障",
        "iconType": 0
      },
      "enterGardenDesc": "消费者成功预订门票并按产品规则使用，出游当日无法按照原订单入园，联系供应商（或去哪儿网）后10分钟未解决，消费者可在景区购买门市价入园并保留票根，去哪儿网将双倍赔付差价。",
      "businessLicenceScheme": "https://touch.piao.qunar.com/touch/supplierInfo.htm?supplierId=11488&licenceType=businessLicence",
      "businessLicenceTitle": "查看",
      "businessLicenceDesc": "《工商执照信息》"
    },
    "bookinfos": {
      "title": "购票须知",
      "bookDescription": {
        "titleInfo": {
          "title": "预订说明",
          "iconUrl": "https://img1.qunarzz.com/piao/fusion/1804/c0/82112e1e4b4fe02.png",
          "desc": "",
          "strongDesc": "",
          "notice": ""
        },
        "contents": [
          {
            "title": "预订时间：",
            "iconUrl": "",
            "desc": "需要在游玩当天的15:30前预订",
            "strongDesc": "",
            "notice": "可订明日"
          },
          {
            "title": "有 效 期：",
            "iconUrl": "",
            "desc": "游玩日期7天内有效",
            "strongDesc": ""
          }
        ]
      },
      "enterGardenDescription": {
        "enterGardenTitle": {
          "title": "入园须知",
          "iconUrl": "https://img1.qunarzz.com/piao/fusion/1804/c0/82112e1e4b4fe02.png"
        },
        "notice": "无需换票，快速入园",
        "enterType": {
          "title": "入园方式：",
          "titleInfo": {
            "title": "入园方式：",
            "iconUrl": "",
            "desc": "",
            "strongDesc": "",
            "notice": "无需换票，快速入园"
          },
          "contents": [
            {
              "titleInfo": {
                "title": "凭去哪儿发送的电子票、身份证在杭州市法云弄1号飞来峰检票处直接验证入园"
              },
              "contents": []
            }
          ]
        },
        "sightOpenTime": {
          "title": "景区开放时间：",
          "desc": "07:30～17:00开放，15:30停止入园；"
        }
      },
      "refundDescription": {
        "titleInfo": {
          "title": "退款说明",
          "iconUrl": "https://img1.qunarzz.com/piao/fusion/1804/c0/82112e1e4b4fe02.png"
        },
        "contents": [
          {
            "title": "退款规则：",
            "desc": "使用日期截止后7天23:59前可申请退款<br/>不支持部分退款<br/>",
            "notice": "条件退"
          },
          {
            "title": "极速处理：",
            "desc": "去哪儿网承诺，提交申请后一个工作日内完成退款申请的审核"
          }
        ]
      },
      "feeDescription": {
        "title": "费用说明",
        "iconUrl": "https://img1.qunarzz.com/piao/fusion/1804/c0/82112e1e4b4fe02.png",
        "desc": "含杭州灵隐飞来峰门票（含灵隐飞来峰大门票、永福寺门票、韬光寺门票；不含灵隐寺门票）成人票，包含一位成人。 进入寺庙必须购买飞来峰门票，灵隐寺门票现场另付）。"
      },
      "usingDescription": {
        "title": "使用说明",
        "iconUrl": "https://img1.qunarzz.com/piao/fusion/1804/c0/82112e1e4b4fe02.png",
        "desc": "【优惠政策】<br/>1、1.2米以下儿童免票，1.2米-1.5米儿童半票，1.5米以上全票。<br/>2、国内60-69周岁老年人凭居民身份证实行半价优惠，国内70周岁及以上老人、现役军人、残疾人、离休干 部、浙江省内30年以上教龄的教师凭有效证件免费参观（仅供参考）。<br/>【温馨提示】此门票不包含灵隐寺门票，如果您要进灵隐寺，请进入飞来峰景区后另行购买灵隐寺门票。"
      },
      "riskTipsInfo": {
        "title": "温馨提示",
        "desc": "1.去哪儿网提醒您注意人身安全，参加有一定危险性的室内或户外活动（如跳伞、潜水、滑雪等）前，请务必仔细阅读<a target=\"_blank\" href=\"https://yun.qunar.com/uploads2/notice/20180801/HighRiskProjectWarning.pdf \" class=\"mp-risklink\" mp-role=\"riskLink\">《高风险项目警示》</a>。<br/>2.为普及旅游安全知识及旅游文明公约，使您的旅程顺利圆满完成，特制定<a target=\"_blank\" href=\"https://yun.qunar.com/uploads2/notice/20180711/travelnotes.pdf \" class=\"mp-risklink\" mp-role=\"riskLink\">《去哪儿网旅游安全手册》</a>，请您认真阅读并切实遵守。",
        "strongDescDetails": [
          {
            "strongDesc": "《高风险项目警示》",
            "url": "https://yun.qunar.com/uploads2/notice/20180801/HighRiskProjectWarning.pdf"
          },
          {
            "strongDesc": "《去哪儿网旅游安全手册》",
            "url": "https://yun.qunar.com/uploads2/notice/20180711/travelnotes.pdf"
          }
        ]
      }
    },
    "supplierName": "去哪儿直销",
    "ticketName": "飞来峰（不含灵隐寺）门票",
    "isQunarPreference": false,
    "payWay": "PREPAY",
    "qunarPrice": "45",
    "encryptSupplierId": "2763243622",
    "shopNameType": "QUNAR_STRAIGHT"
  },
  "version": 1.0
}